[
	{
    "PolicyName": "SCC_SecurityLevel_Security Level Number",
    "Publisher": [
        {
            "name": "Publisher name",
            "URL": "URL corresponding to publisher"
        }
    ],
    "SecurityLevel" : "Security Level Number",
    "Version": "YYYY-Patch",
    "PolicyIssueDate": "YYYY-MM-DD",
    "Expiry": "YYYY-MM-DD",
    "Usage": {
        "SymmetricEncryption": [
            "Algorithm 1",
            "Algorithm 2"
        ],
        "AsymmetricEncryption": [
            "Algorithm 1",
            "Algorithm 2"
        ],
        "Hashing": [
            "Algorithm 1",
            "Algorithm 2"
        ],
        "PasswordHashing": [
            "Algorithm 1",
            "Algorithm 2"
        ],
        "Signing": [
            "Algorithm 1",
            "Algorithm 2"
        ]
    }
  }
]